Metadata-Version: 1.0
Name: alfred-workflow-flyer
Version: 0.0.3
Summary: A simple scaffold of alfred workflow
Home-page: UNKNOWN
Author: Pushy
Author-email: 1437876073@qq.com
License: UNKNOWN
Platform: UNKNOWN
